[
    {
        "@_fa": "true",
        "link": [
            {
                "@_fa": "true",
                "@ref": "self",
                "@href": "https://api.elsevier.com/content/abstract/scopus_id/85085743228"
            },
            {
                "@_fa": "true",
                "@ref": "author-affiliation",
                "@href": "https://api.elsevier.com/content/abstract/scopus_id/85085743228?field=author,affiliation"
            },
            {
                "@_fa": "true",
                "@ref": "scopus",
                "@href": "https://www.scopus.com/inward/record.uri?partnerID=HzOxMe3b&scp=85085743228&origin=inward"
            },
            {
                "@_fa": "true",
                "@ref": "scopus-citedby",
                "@href": "https://www.scopus.com/inward/citedby.uri?partnerID=HzOxMe3b&scp=85085743228&origin=inward"
            }
        ],
        "prism:url": "https://api.elsevier.com/content/abstract/scopus_id/85085743228",
        "dc:identifier": "SCOPUS_ID:85085743228",
        "eid": "2-s2.0-85085743228",
        "dc:title": "A comparative analysis of mono-tube shock absorbers with different valve systems",
        "dc:creator": "Ferdek U.",
        "prism:publicationName": "AIP Conference Proceedings",
        "prism:issn": "0094243X",
        "prism:eIssn": "15517616",
        "prism:isbn": [
            {
                "@_fa": "true",
                "$": "9780735419988"
            }
        ],
        "prism:volume": "2239",
        "prism:pageRange": null,
        "prism:coverDate": "2020-05-22",
        "prism:coverDisplayDate": "22 May 2020",
        "prism:doi": "10.1063/5.0007803",
        "citedby-count": "0",
        "affiliation": [
            {
                "@_fa": "true",
                "affilname": "Politechnika Krakowska",
                "affiliation-city": "Krakow",
                "affiliation-country": "Poland"
            }
        ],
        "prism:aggregationType": "Conference Proceeding",
        "subtype": "cp",
        "subtypeDescription": "Conference Paper",
        "article-number": "020010",
        "source-id": "26916",
        "openaccess": "1",
        "openaccessFlag": true,
        "freetoread": {
            "value": [
                {
                    "$": "all"
                },
                {
                    "$": "publisherfree2read"
                }
            ]
        },
        "freetoreadLabel": {
            "value": [
                {
                    "$": "All Open Access"
                },
                {
                    "$": "Bronze"
                }
            ]
        }
    },
    {
        "@_fa": "true",
        "link": [
            {
                "@_fa": "true",
                "@ref": "self",
                "@href": "https://api.elsevier.com/content/abstract/scopus_id/85083686799"
            },
            {
                "@_fa": "true",
                "@ref": "author-affiliation",
                "@href": "https://api.elsevier.com/content/abstract/scopus_id/85083686799?field=author,affiliation"
            },
            {
                "@_fa": "true",
                "@ref": "scopus",
                "@href": "https://www.scopus.com/inward/record.uri?partnerID=HzOxMe3b&scp=85083686799&origin=inward"
            },
            {
                "@_fa": "true",
                "@ref": "scopus-citedby",
                "@href": "https://www.scopus.com/inward/citedby.uri?partnerID=HzOxMe3b&scp=85083686799&origin=inward"
            }
        ],
        "prism:url": "https://api.elsevier.com/content/abstract/scopus_id/85083686799",
        "dc:identifier": "SCOPUS_ID:85083686799",
        "eid": "2-s2.0-85083686799",
        "dc:title": "Nonlinear dynamics of a vehicle with a displacement-sensitive mono-tube shock absorber",
        "dc:creator": "Łuczko J.",
        "prism:publicationName": "Nonlinear Dynamics",
        "prism:issn": "0924090X",
        "prism:eIssn": "1573269X",
        "prism:volume": "100",
        "prism:issueIdentifier": "1",
        "prism:pageRange": "185-202",
        "prism:coverDate": "2020-03-01",
        "prism:coverDisplayDate": "1 March 2020",
        "prism:doi": "10.1007/s11071-020-05532-7",
        "citedby-count": "2",
        "affiliation": [
            {
                "@_fa": "true",
                "affilname": "Politechnika Krakowska",
                "affiliation-city": "Krakow",
                "affiliation-country": "Poland"
            }
        ],
        "prism:aggregationType": "Journal",
        "subtype": "ar",
        "subtypeDescription": "Article",
        "source-id": "21576",
        "openaccess": "1",
        "openaccessFlag": true,
        "freetoread": {
            "value": [
                {
                    "$": "all"
                },
                {
                    "$": "publisherhybridgold"
                }
            ]
        },
        "freetoreadLabel": {
            "value": [
                {
                    "$": "All Open Access"
                },
                {
                    "$": "Hybrid Gold"
                }
            ]
        }
    },
    {
        "@_fa": "true",
        "link": [
            {
                "@_fa": "true",
                "@ref": "self",
                "@href": "https://api.elsevier.com/content/abstract/scopus_id/85048417899"
            },
            {
                "@_fa": "true",
                "@ref": "author-affiliation",
                "@href": "https://api.elsevier.com/content/abstract/scopus_id/85048417899?field=author,affiliation"
            },
            {
                "@_fa": "true",
                "@ref": "scopus",
                "@href": "https://www.scopus.com/inward/record.uri?partnerID=HzOxMe3b&scp=85048417899&origin=inward"
            },
            {
                "@_fa": "true",
                "@ref": "scopus-citedby",
                "@href": "https://www.scopus.com/inward/citedby.uri?partnerID=HzOxMe3b&scp=85048417899&origin=inward"
            },
            {
                "@_fa": "true",
                "@ref": "full-text",
                "@href": "https://api.elsevier.com/content/article/eid/1-s2.0-S0888327018303443"
            }
        ],
        "prism:url": "https://api.elsevier.com/content/abstract/scopus_id/85048417899",
        "dc:identifier": "SCOPUS_ID:85048417899",
        "eid": "2-s2.0-85048417899",
        "dc:title": "Non-linear analysis of a quarter-car model with stroke-dependent twin-tube shock absorber",
        "dc:creator": "Łuczko J.",
        "prism:publicationName": "Mechanical Systems and Signal Processing",
        "prism:issn": "08883270",
        "prism:eIssn": "10961216",
        "prism:volume": "115",
        "prism:pageRange": "450-468",
        "prism:coverDate": "2019-01-15",
        "prism:coverDisplayDate": "15 January 2019",
        "prism:doi": "10.1016/j.ymssp.2018.06.008",
        "pii": "S0888327018303443",
        "citedby-count": "7",
        "affiliation": [
            {
                "@_fa": "true",
                "affilname": "Politechnika Krakowska",
                "affiliation-city": "Krakow",
                "affiliation-country": "Poland"
            }
        ],
        "prism:aggregationType": "Journal",
        "subtype": "ar",
        "subtypeDescription": "Article",
        "source-id": "21080",
        "openaccess": "0",
        "openaccessFlag": false
    },
    {
        "@_fa": "true",
        "link": [
            {
                "@_fa": "true",
                "@ref": "self",
                "@href": "https://api.elsevier.com/content/abstract/scopus_id/85041051505"
            },
            {
                "@_fa": "true",
                "@ref": "author-affiliation",
                "@href": "https://api.elsevier.com/content/abstract/scopus_id/85041051505?field=author,affiliation"
            },
            {
                "@_fa": "true",
                "@ref": "scopus",
                "@href": "https://www.scopus.com/inward/record.uri?partnerID=HzOxMe3b&scp=85041051505&origin=inward"
            },
            {
                "@_fa": "true",
                "@ref": "scopus-citedby",
                "@href": "https://www.scopus.com/inward/citedby.uri?partnerID=HzOxMe3b&scp=85041051505&origin=inward"
            }
        ],
        "prism:url": "https://api.elsevier.com/content/abstract/scopus_id/85041051505",
        "dc:identifier": "SCOPUS_ID:85041051505",
        "eid": "2-s2.0-85041051505",
        "dc:title": "Nonlinear analysis of shock absorbers with amplitude-dependent damping",
        "dc:creator": "Łuczko J.",
        "prism:publicationName": "AIP Conference Proceedings",
        "prism:issn": "0094243X",
        "prism:eIssn": "15517616",
        "prism:isbn": [
            {
                "@_fa": "true",
                "$": "9780735416147"
            }
        ],
        "prism:volume": "1922",
        "prism:pageRange": null,
        "prism:coverDate": "2018-01-05",
        "prism:coverDisplayDate": "5 January 2018",
        "prism:doi": "10.1063/1.5019096",
        "citedby-count": "1",
        "affiliation": [
            {
                "@_fa": "true",
                "affilname": "Politechnika Krakowska",
                "affiliation-city": "Krakow",
                "affiliation-country": "Poland"
            }
        ],
        "prism:aggregationType": "Conference Proceeding",
        "subtype": "cp",
        "subtypeDescription": "Conference Paper",
        "article-number": "100011",
        "source-id": "26916",
        "openaccess": "1",
        "openaccessFlag": true,
        "freetoread": {
            "value": [
                {
                    "$": "all"
                },
                {
                    "$": "publisherfree2read"
                }
            ]
        },
        "freetoreadLabel": {
            "value": [
                {
                    "$": "All Open Access"
                },
                {
                    "$": "Bronze"
                }
            ]
        }
    },
    {
        "@_fa": "true",
        "link": [
            {
                "@_fa": "true",
                "@ref": "self",
                "@href": "https://api.elsevier.com/content/abstract/scopus_id/85054936524"
            },
            {
                "@_fa": "true",
                "@ref": "author-affiliation",
                "@href": "https://api.elsevier.com/content/abstract/scopus_id/85054936524?field=author,affiliation"
            },
            {
                "@_fa": "true",
                "@ref": "scopus",
                "@href": "https://www.scopus.com/inward/record.uri?partnerID=HzOxMe3b&scp=85054936524&origin=inward"
            },
            {
                "@_fa": "true",
                "@ref": "scopus-citedby",
                "@href": "https://www.scopus.com/inward/citedby.uri?partnerID=HzOxMe3b&scp=85054936524&origin=inward"
            }
        ],
        "prism:url": "https://api.elsevier.com/content/abstract/scopus_id/85054936524",
        "dc:identifier": "SCOPUS_ID:85054936524",
        "eid": "2-s2.0-85054936524",
        "dc:title": "Nonlinear modeling and analysis of a shock absorber with a bypass",
        "dc:creator": "Ferdek U.",
        "prism:publicationName": "Journal of Theoretical and Applied Mechanics (Poland)",
        "prism:issn": "14292955",
        "prism:volume": "56",
        "prism:issueIdentifier": "3",
        "prism:pageRange": "615-629",
        "prism:coverDate": "2018-01-01",
        "prism:coverDisplayDate": "2018",
        "prism:doi": "10.15632/jtam-pl.56.3.615",
        "citedby-count": "6",
        "affiliation": [
            {
                "@_fa": "true",
                "affilname": "Politechnika Krakowska",
                "affiliation-city": "Krakow",
                "affiliation-country": "Poland"
            }
        ],
        "prism:aggregationType": "Journal",
        "subtype": "ar",
        "subtypeDescription": "Article",
        "source-id": "19700176043",
        "openaccess": "1",
        "openaccessFlag": true,
        "freetoread": {
            "value": [
                {
                    "$": "all"
                },
                {
                    "$": "publisherfullgold"
                }
            ]
        },
        "freetoreadLabel": {
            "value": [
                {
                    "$": "All Open Access"
                },
                {
                    "$": "Gold"
                }
            ]
        }
    }
]